nawah/__init__.py
nawah/__main__.py
nawah/py.typed
nawah/base/__init__.py
nawah/base/_create.py
nawah/base/_delete.py
nawah/base/_delete_file.py
nawah/base/_delete_lock.py
nawah/base/_obtain_lock.py
nawah/base/_read.py
nawah/base/_read_diff.py
nawah/base/_retrieve_file.py
nawah/base/_shared.py
nawah/base/_update.py
nawah/base/_update_file.py
nawah/base/exceptions.py
nawah/base/py.typed
nawah/base/_create_file/__init__.py
nawah/base/_create_file/_classes.py
nawah/base/_create_file/_funcs.py
nawah/classes/__init__.py
nawah/classes/_attr.py
nawah/classes/_cache.py
nawah/classes/_client_app.py
nawah/classes/_counter.py
nawah/classes/_default.py
nawah/classes/_diff.py
nawah/classes/_encoders.py
nawah/classes/_extn.py
nawah/classes/_func.py
nawah/classes/_jsonpath.py
nawah/classes/_l10n.py
nawah/classes/_module.py
nawah/classes/_package.py
nawah/classes/_py_plausible.py
nawah/classes/_query.py
nawah/classes/_sys_doc.py
nawah/classes/_user_attr.py
nawah/classes/_var.py
nawah/classes/py.typed
nawah/cli/__init__.py
nawah/cli/_cli.py
nawah/cli/_create.py
nawah/cli/_serve.py
nawah/cli/py.typed
nawah/cli/_generate/__init__.py
nawah/cli/_generate/_generate_models_dart.py
nawah/cli/_generate/_generate_models_ts.py
nawah/cli/_generate/py.typed
nawah/config/__init__.py
nawah/config/_config.py
nawah/config/py.typed
nawah/data/__init__.py
nawah/data/_conn.py
nawah/data/_create.py
nawah/data/_delete.py
nawah/data/_drop.py
nawah/data/_query.py
nawah/data/_read.py
nawah/data/_update.py
nawah/data/py.typed
nawah/enums/__init__.py
nawah/enums/_enums.py
nawah/enums/py.typed
nawah/exceptions/__init__.py
nawah/exceptions/_attr.py
nawah/exceptions/_call.py
nawah/exceptions/_config.py
nawah/exceptions/_data.py
nawah/exceptions/_func.py
nawah/exceptions/_query.py
nawah/exceptions/_validate.py
nawah/exceptions/_var.py
nawah/exceptions/py.typed
nawah/packages/__init__.py
nawah/packages/py.typed
nawah/packages/core/__init__.py
nawah/packages/core/py.typed
nawah/packages/core/base/__init__.py
nawah-2.0b40.dist-info/LICENSE
nawah-2.0b40.dist-info/METADATA
nawah-2.0b40.dist-info/WHEEL
nawah-2.0b40.dist-info/top_level.txt
nawah-2.0b40.dist-info/RECORD
