Metadata-Version: 2.1
Name: nawah
Version: 2.0b40
Summary: Nawah--Rapid, cloud-native app development framework
Author-email: Mahmoud Abduljawad <me@mahmoudajawad.com>
License: AGPLv3
Keywords: development,framework,cloud-native,test-driven development,domain-driven design,behavior-driven development,event-driven architecture,platform
Classifier: Programming Language :: Python :: 3
Classifier: Programming Language :: Python :: 3.10
Classifier: Development Status :: 5 - Production/Stable
Classifier: License :: OSI Approved :: GNU Affero General Public License v3 or later (AGPLv3+)
Classifier: Operating System :: OS Independent
Classifier: Topic :: Internet :: WWW/HTTP
Classifier: Framework :: AsyncIO
Requires-Python: >=3.12
License-File: LICENSE
Requires-Dist: aiohttp ==3.8.3
Requires-Dist: aiodns ==3.0.0
Requires-Dist: motor ==3.1.1
Requires-Dist: passlib ==1.7.4
Requires-Dist: Pillow ==9.3.0
Requires-Dist: PyJWT ==2.6.0
Requires-Dist: pymongo ==4.3.2
Requires-Dist: requests ==2.28.1
Requires-Dist: requests-toolbelt ==0.10.1
Requires-Dist: hiredis ==2.4.0
Requires-Dist: redis ==4.3.4
Requires-Dist: sentry-sdk ==1.10.1
Requires-Dist: click ==8.1.3
Provides-Extra: dev
Requires-Dist: build >=1.2.0 ; extra == 'dev'
Requires-Dist: mock >=4.0.3 ; extra == 'dev'
Requires-Dist: codecov >=2.1.12 ; extra == 'dev'
Requires-Dist: mypy >=0.990 ; extra == 'dev'
Requires-Dist: black >=22.10.0 ; extra == 'dev'
Requires-Dist: pylint >=2.15.5 ; extra == 'dev'
Requires-Dist: pytest >=7.2.0 ; extra == 'dev'
Requires-Dist: pytest-asyncio >=0.20.1 ; extra == 'dev'
Requires-Dist: pytest-mock >=3.10.0 ; extra == 'dev'
Requires-Dist: pytest-cov >=4.0.0 ; extra == 'dev'
Requires-Dist: python-lsp-server >=1.6.0 ; extra == 'dev'
Requires-Dist: pylsp-mypy >=0.6.3 ; extra == 'dev'
Requires-Dist: python-lsp-black >=1.2.1 ; extra == 'dev'
Requires-Dist: setuptools >=74.0.0 ; extra == 'dev'
Requires-Dist: setuptools-scm >=8.1.0 ; extra == 'dev'
Requires-Dist: wheel >=0.38.2 ; extra == 'dev'
Requires-Dist: twine >=4.0.1 ; extra == 'dev'
Requires-Dist: types-redis >=4.3.21.3 ; extra == 'dev'
Requires-Dist: types-requests >=2.28.11.2 ; extra == 'dev'
Requires-Dist: types-mock >=4.0.15.2 ; extra == 'dev'
